teslaapi/__init__.py
teslaapi/teslaapi.py
tesla_api_py-1.3.1.dist-info/METADATA
tesla_api_py-1.3.1.dist-info/WHEEL
tesla_api_py-1.3.1.dist-info/top_level.txt
tesla_api_py-1.3.1.dist-info/RECORD
