Metadata-Version: 2.1
Name: tesla-api-py
Version: 1.3.1
Summary: Tesla api 
Home-page: https://github.com/zcq100/teslaapi
Author: zcq100
Author-email: zcq100@gmail.com
License: Apache License
Platform: UNKNOWN
Classifier: Topic :: Utilities
Classifier: Topic :: Internet
Classifier: Topic :: Software Development :: Libraries :: Python Modules
Classifier: Programming Language :: Python
Classifier: Programming Language :: Python :: 3.6
Requires-Python: >=3.5
